Task4/rv32i.v

module rv32i(
	clk,
	rn,
	npc,
	WB_OUT);


input clk;
input rn;


output reg [31:0]WB_OUT;
output reg [31:0]npc;

//input EN;
integer k;
wire  EX_MEM_COND ;

reg 
BR_EN;

//I_FETCH STAGE
reg[31:0] 
IF_ID_IR,
IF_ID_npc;                                

//I_DECODE STAGE
reg[31:0] 
ID_EX_A,
ID_EX_B,
ID_EX_RD,
ID_EX_IMMEDIATE,
ID_EX_IR,ID_EX_npc;      

//EXECUTION STAGE
reg[31:0] 
EX_MEM_ALUOUT,
EX_MEM_B,EX_MEM_IR;                        

parameter 
ADD=3'd0,
SUB=3'd1,
AND=3'd2,
OR=3'd3,
XOR=3'd4,
SLT=3'd5,

ADDI=3'd0,
SUBI=3'd1,
ANDI=3'd2,
ORI=3'd3,
XORI=3'd4,

LW=3'd0,
SW=3'd1,

BEQ=3'd0,
BNE=3'd1,

SLL=3'd0,
SRL=3'd1;


parameter 
AR_TYPE=7'd0,
M_TYPE=7'd1,
BR_TYPE=7'd2,
SH_TYPE=7'd3;


//MEMORY STAGE
reg[31:0] 
MEM_WB_IR,
MEM_WB_ALUOUT,
MEM_WB_LDM;                      




//REG FILE
reg [31:0]REG[0:31];                                               
//64*32 IMEM
reg [31:0]MEM[0:31];                                             
//64*32 DMEM
reg [31:0]DM[0:31];   


//assign EX_MEM_COND = (EX_MEM_IR[6:0]==BR_TYPE) ? 1'b1 : 1'b0;
                     //1'b1 ? (ID_EX_A!=ID_EX_RD) : 1'b0;

always @(posedge clk or posedge rn) begin
    if(rn) begin
    npc<= 32'd0;
    //EX_MEM_COND <=1'd0;
    BR_EN<= 1'd0; 
    REG[0] <= 32'h00000000;
    REG[1] <= 32'd1;
    REG[2] <= 32'd2;
    REG[3] <= 32'd3;
    REG[4] <= 32'd4;
    REG[5] <= 32'd5;
    REG[6] <= 32'd6;
    end
    //else if(EX_MEM_COND)
    //npc <= EX_MEM_ALUOUT;

    //else if (EX_MEM_COND)begin
    //npc = EX_MEM_COND ? EX_MEM_ALUOUT : npc +32'd1;
    //npc <= EX_MEM_ALUOUT;
    //EX_MEM_COND = BR_EN;
    //npc = BR_EN ? EX_MEM_ALUOUT : npc +32'd1;
    //BR_EN = 1'd0;
    //EX_MEM_COND <= 1'd0;
    //end
    else begin
    npc <= BR_EN ? EX_MEM_ALUOUT : npc +32'd1;
    BR_EN <= 1'd0;
    //npc <= npc +32'd1;
    //EX_MEM_COND <=1'd0;
    IF_ID_IR <=MEM[npc];
    IF_ID_npc <=npc+32'd1;
    end
end

always @(posedge rn) begin
    //npc<= 32'd0;
MEM[0] <= 32'h02208300;         // add r6,r1,r2.(i1)
MEM[1] <= 32'h02209380;         //sub r7,r1,r2.(i2)
MEM[2] <= 32'h0230a400;         //and r8,r1,r3.(i3)
MEM[3] <= 32'h02513480;         //or r9,r2,r5.(i4)
MEM[4] <= 32'h0240c500;         //xor r10,r1,r4.(i5)
MEM[5] <= 32'h02415580;         //slt r11,r2,r4.(i6)
MEM[6] <= 32'h00520600;         //addi r12,r4,5.(i7)
MEM[7] <= 32'h00209181;         //sw r3,r1,2.(i8)
MEM[8] <= 32'h00208681;         //lw r13,r1,2.(i9)
MEM[9] <= 32'h00f00002;         //beq r0,r0,15.(i10)
MEM[25] <= 32'h00210700;         //add r14,r2,r2.(i11)
//MEM[27] <= 32'h01409002;         //bne r0,r1,20.(i12)
//MEM[49] <= 32'h00520601;         //addi r12,r4,5.(i13)
//MEM[50] <= 32'h00208783;         //sll r15,r1,r2(2).(i14)
//MEM[51] <= 32'h00271803;         //srl r16,r14,r2(2).(i15) */

//for(k=0;k<=31;k++)
//REG[k]<=k;
/*REG[0] <= 32'h00000000;
REG[1] <= 32'd1;
REG[2] <= 32'd2;
REG[3] <= 32'd3;
REG[4] <= 32'd4;
REG[5] <= 32'd5;
REG[6] <= 32'd6;
REG[7] = 32'd7;
REG[6] = 32'd6;
REG[7] = 32'd7;
REG[8] = 32'd8;
REG[9] = 32'd9;
REG[10] = 32'd10;
REG[11] = 32'd11;
REG[12] = 32'd12;
REG[13] = 32'd13;
REG[14] = 32'd14;
REG[15] = 32'd15;
REG[16] = 32'd16;
REG[17] = 32'd17;*/
/*end
else begin
    if(EX_MEM_COND==1 && EX_MEM_IR[6:0]==BR_TYPE) begin
    npc=EX_MEM_ALUOUT;
    IF_ID=MEM[npc];
    end

    else begin
    npc<=npc+32'd1;
    IF_ID<=MEM[npc];
    IF_ID_npc<=npcC+32'd1;
    end
end*/
end
//I_FECT STAGE

/*always @(posedge clk) begin

//npc <= rst ? 32'd0 : npc+32'd1;

if(EX_MEM_COND==1 && EX_MEM_IR[6:0]==BR_TYPE) begin
npc=EX_MEM_ALUOUT;
IF_ID=MEM[npc];
end

else begin
npc<=npc+32'd1;
IF_ID<=MEM[npc];
IF_ID_npc<=npc+32'd1;
end
end*/


//FETCH STAGE END

//I_DECODE STAGE 
always @(posedge clk) begin

ID_EX_A <= REG[IF_ID_IR[19:15]];
ID_EX_B <= REG[IF_ID_IR[24:20]];
ID_EX_RD <= REG[IF_ID_IR[11:7]];
ID_EX_IR <= IF_ID_IR;
ID_EX_IMMEDIATE <= {{20{IF_ID_IR[31]}},IF_ID_IR[31:20]};
ID_EX_npc<=IF_ID_npc;
end
//DECODE STAGE END

/*always@(posedge clk) begin
if(ID_EX_IR[6:0]== BR_TYPE)
EX_MEM_COND <= EN;
else
EX_MEM_COND <= !EN;
end*/


//EXECUTION STAGE

always@(posedge clk) begin

EX_MEM_IR <=  ID_EX_IR;
//EX_MEM_COND <= (ID_EX_IR[6:0] == BR_TYPE) ? 1'd1 :1'd0;


case(ID_EX_IR[6:0])

AR_TYPE:begin
    if(ID_EX_IR[31:25]== 7'd1)begin
    case(ID_EX_IR[14:12])

    ADD:EX_MEM_ALUOUT <= ID_EX_A + ID_EX_B;
    SUB:EX_MEM_ALUOUT <= ID_EX_A - ID_EX_B;
    AND:EX_MEM_ALUOUT <= ID_EX_A & ID_EX_B;
    OR :EX_MEM_ALUOUT <= ID_EX_A | ID_EX_B;
    XOR:EX_MEM_ALUOUT <= ID_EX_A ^ ID_EX_B;
    SLT:EX_MEM_ALUOUT <= (ID_EX_A < ID_EX_B) ? 32'd1 : 32'd0;

    endcase
    end
    else begin
        case(ID_EX_IR[14:12])
        ADDI:EX_MEM_ALUOUT <= ID_EX_A + ID_EX_IMMEDIATE;
        SUBI:EX_MEM_ALUOUT <= ID_EX_A - ID_EX_IMMEDIATE;
        ANDI:EX_MEM_ALUOUT <= ID_EX_A & ID_EX_B;
        ORI:EX_MEM_ALUOUT  <= ID_EX_A | ID_EX_B;
        XORI:EX_MEM_ALUOUT <= ID_EX_A ^ ID_EX_B;
        endcase
    end

end

M_TYPE:begin
    case(ID_EX_IR[14:12])
    LW  :EX_MEM_ALUOUT <= ID_EX_A + ID_EX_IMMEDIATE;
    SW  :EX_MEM_ALUOUT <= ID_EX_IR[24:20] + ID_EX_IR[19:15];
    endcase
end

BR_TYPE:begin
    case(ID_EX_IR[14:12])
    BEQ:begin 
    EX_MEM_ALUOUT <= ID_EX_npc+ID_EX_IMMEDIATE;
    BR_EN <= 1'd1 ? (ID_EX_IR[19:15] == ID_EX_IR[11:7]) : 1'd0;
    //BR_PC = EX_MEM_COND ? EX_MEM_ALUOUT : 1'd0; 
end
BNE:begin 
    EX_MEM_ALUOUT <= ID_EX_npc+ID_EX_IMMEDIATE;
    BR_EN <= (ID_EX_IR[19:15] != ID_EX_IR[11:7]) ? 1'd1 : 1'd0;
end
endcase
end

SH_TYPE:begin
case(ID_EX_IR[14:12])
SLL:EX_MEM_ALUOUT <= ID_EX_A << ID_EX_B;
SRL:EX_MEM_ALUOUT <= ID_EX_A >> ID_EX_B;
endcase
end

endcase
end


//EXECUTION STAGE END
		
//MEMORY STAGE
always@(posedge clk) begin

MEM_WB_IR <= EX_MEM_IR;

case(EX_MEM_IR[6:0])

AR_TYPE:MEM_WB_ALUOUT <=  EX_MEM_ALUOUT;
SH_TYPE:MEM_WB_ALUOUT <=  EX_MEM_ALUOUT;

M_TYPE:begin
case(EX_MEM_IR[14:12])
LW:MEM_WB_LDM <= DM[EX_MEM_ALUOUT];
SW:DM[EX_MEM_ALUOUT]<=REG[EX_MEM_IR[11:7]];
endcase
end

endcase
end

// MEMORY STAGE END


//WRITE BACK STAGE
always@(posedge clk) begin

case(MEM_WB_IR[6:0])

AR_TYPE:begin 
WB_OUT<=MEM_WB_ALUOUT;
REG[MEM_WB_IR[11:7]]<=MEM_WB_ALUOUT;
end

SH_TYPE:begin
WB_OUT<=MEM_WB_ALUOUT;
REG[MEM_WB_IR[11:7]]<=MEM_WB_ALUOUT;
end

M_TYPE:begin
case(MEM_WB_IR[14:12])
LW:begin
WB_OUT<=MEM_WB_LDM;
REG[MEM_WB_IR[11:7]]<=MEM_WB_LDM;
end
endcase
end



endcase
end
//WRITE BACK STAGE END

endmodule

Task4/rv32i_tb.v
module rv32i_tb;

reg clk;
reg rn;
wire [31:0]WB_OUT;
wire [31:0]npc;

rv32i dut (
	.clk(clk),
	.rn(rn),
	.npc(npc),
	.WB_OUT(WB_OUT)

	);


always #3  clk=!clk;

initial begin 

rn  = 1'b1;
clk = 1'b1;

$dumpfile ("rv32i_tb.vcd"); //by default vcd
$dumpvars (0, dut);
  
  #5 rn = 1'b0;
  
  #300 $finish;

end
endmodule

Task4/rv32i_tb.vcd
$date
	Mon Sep  8 23:10:05 2025
$end
$version
	Icarus Verilog
$end
$timescale
	1s
$end
$scope module rv32i_tb $end
$scope module dut $end
$var wire 1 ! clk $end
$var wire 1 " rn $end
$var reg 1 # BR_EN $end
$var reg 32 $ EX_MEM_ALUOUT [31:0] $end
$var reg 32 % EX_MEM_IR [31:0] $end
$var reg 32 & ID_EX_A [31:0] $end
$var reg 32 ' ID_EX_B [31:0] $end
$var reg 32 ( ID_EX_IMMEDIATE [31:0] $end
$var reg 32 ) ID_EX_IR [31:0] $end
$var reg 32 * ID_EX_RD [31:0] $end
$var reg 32 + ID_EX_npc [31:0] $end
$var reg 32 , IF_ID_IR [31:0] $end
$var reg 32 - IF_ID_npc [31:0] $end
$var reg 32 . MEM_WB_ALUOUT [31:0] $end
$var reg 32 / MEM_WB_IR [31:0] $end
$var reg 32 0 MEM_WB_LDM [31:0] $end
$var reg 32 1 WB_OUT [31:0] $end
$var reg 32 2 npc [31:0] $end
$upscope $end
$upscope $end
$enddefinitions $end
#0
$dumpvars
b0 2
bx 1
bx 0
bx /
bx .
bx -
bx ,
bx +
bx *
bx )
bx (
bx '
bx &
bx %
bx $
0#
1"
1!
$end
#3
0!
#5
0"
#6
b1 -
b10001000001000001100000000 ,
b1 2
1!
#9
0!
#12
b1 +
b100010 (
b10001000001000001100000000 )
b110 *
b10 '
b1 &
b10 -
b10001000001001001110000000 ,
b10 2
1!
#15
0!
#18
b11 $
b10001000001000001100000000 %
b10 +
b10001000001001001110000000 )
bx *
b11 -
b10001100001010010000000000 ,
b11 2
1!
#21
0!
#24
b11 +
b100011 (
b10001100001010010000000000 )
b11 '
b11111111111111111111111111111111 $
b10001000001001001110000000 %
b11 .
b10001000001000001100000000 /
b100 -
b10010100010011010010000000 ,
b100 2
1!
#27
0!
#30
b11 1
b11111111111111111111111111111111 .
b10001000001001001110000000 /
b1 $
b10001100001010010000000000 %
b100 +
b100101 (
b10010100010011010010000000 )
b101 '
b10 &
b101 -
b10010000001100010100000000 ,
b101 2
1!
#33
0!
#36
b101 +
b100100 (
b10010000001100010100000000 )
b100 '
b1 &
b111 $
b10010100010011010010000000 %
b1 .
b10001100001010010000000000 /
b11111111111111111111111111111111 1
b110 -
b10010000010101010110000000 ,
b110 2
1!
#39
0!
#42
b1 1
b111 .
b10010100010011010010000000 /
b101 $
b10010000001100010100000000 %
b110 +
b10010000010101010110000000 )
b10 &
b111 -
b10100100000011000000000 ,
b111 2
1!
#45
0!
#48
b111 +
b101 (
b10100100000011000000000 )
b101 '
b100 &
b1 $
b10010000010101010110000000 %
b101 .
b10010000001100010100000000 /
b111 1
b1000 -
b1000001001000110000001 ,
b1000 2
1!
#51
0!
#54
b101 1
b1 .
b10010000010101010110000000 /
b1001 $
b10100100000011000000000 %
b1000 +
b10 (
b1000001001000110000001 )
b11 *
b10 '
b1 &
b1001 -
b1000001000011010000001 ,
b1001 2
1!
#57
0!
#60
b1001 +
b1000001000011010000001 )
bx *
b11 $
b1000001001000110000001 %
b1001 .
b10100100000011000000000 /
b1 1
b1010 -
b111100000000000000000010 ,
b1010 2
1!
#63
0!
#66
b1001 1
b1000001001000110000001 /
b1000001000011010000001 %
b1010 +
b1111 (
b111100000000000000000010 )
b0 *
bx '
b0 &
b1011 -
bx ,
b1011 2
1!
#69
0!
#72
b1011 +
bx (
bx )
bx *
bx &
1#
b11001 $
b111100000000000000000010 %
b11 0
b1000001000011010000001 /
b1100 -
b1100 2
1!
#75
0!
#78
b11 1
b111100000000000000000010 /
bx %
b1100 +
b1101 -
0#
b11001 2
1!
#81
0!
#84
b1101 +
bx /
b11010 -
b1000010000011100000000 ,
b11010 2
1!
#87
0!
#90
b11010 +
b10 (
b1000010000011100000000 )
b10 '
b10 &
b11011 -
bx ,
b11011 2
1!
#93
0!
#96
b11011 +
bx (
bx )
bx '
bx &
b100 $
b1000010000011100000000 %
b11100 -
b11100 2
1!
#99
0!
#102
b100 .
b1000010000011100000000 /
bx %
b11100 +
b11101 -
b11101 2
1!
#105
0!
#108
b11101 +
bx /
b100 1
b11110 -
b11110 2
1!
#111
0!
#114
b11110 +
b11111 -
b11111 2
1!
#117
0!
#120
b11111 +
b100000 -
b100000 2
1!
#123
0!
#126
b100000 +
b100001 -
b100001 2
1!
#129
0!
#132
b100001 +
b100010 -
b100010 2
1!
#135
0!
#138
b100010 +
b100011 -
b100011 2
1!
#141
0!
#144
b100011 +
b100100 -
b100100 2
1!
#147
0!
#150
b100100 +
b100101 -
b100101 2
1!
#153
0!
#156
b100101 +
b100110 -
b100110 2
1!
#159
0!
#162
b100110 +
b100111 -
b100111 2
1!
#165
0!
#168
b100111 +
b101000 -
b101000 2
1!
#171
0!
#174
b101000 +
b101001 -
b101001 2
1!
#177
0!
#180
b101001 +
b101010 -
b101010 2
1!
#183
0!
#186
b101010 +
b101011 -
b101011 2
1!
#189
0!
#192
b101011 +
b101100 -
b101100 2
1!
#195
0!
#198
b101100 +
b101101 -
b101101 2
1!
#201
0!
#204
b101101 +
b101110 -
b101110 2
1!
#207
0!
#210
b101110 +
b101111 -
b101111 2
1!
#213
0!
#216
b101111 +
b110000 -
b110000 2
1!
#219
0!
#222
b110000 +
b110001 -
b110001 2
1!
#225
0!
#228
b110001 +
b110010 -
b110010 2
1!
#231
0!
#234
b110010 +
b110011 -
b110011 2
1!
#237
0!
#240
b110011 +
b110100 -
b110100 2
1!
#243
0!
#246
b110100 +
b110101 -
b110101 2
1!
#249
0!
#252
b110101 +
b110110 -
b110110 2
1!
#255
0!
#258
b110110 +
b110111 -
b110111 2
1!
#261
0!
#264
b110111 +
b111000 -
b111000 2
1!
#267
0!
#270
b111000 +
b111001 -
b111001 2
1!
#273
0!
#276
b111001 +
b111010 -
b111010 2
1!
#279
0!
#282
b111010 +
b111011 -
b111011 2
1!
#285
0!
#288
b111011 +
b111100 -
b111100 2
1!
#291
0!
#294
b111100 +
b111101 -
b111101 2
1!
#297
0!
#300
b111101 +
b111110 -
b111110 2
1!
